Metadata-Version: 2.1
Name: npdtools
Version: 1.0.1
Summary: tool for work with FNS API
Home-page: https://gitlab.com/whiteapfel/npdtools
Author: WhiteApfel
Author-email: white@pfel.ru
License: MPL 2.0
Project-URL: Документация, https://npd-tools.readthedocs.io/en/latest/
Project-URL: Исходники, https://gitlab.com/whiteapfel/npdtools/
Project-URL: По вопросам, https://t.me/apfel
Keywords: FNS API wrapper nalog налог ФНС самозанятость
License-File: LICENSE
Requires-Dist: typing >=3.7.4.3
Requires-Dist: httpx ~=0.24.1
Requires-Dist: python-dateutil >=2.8.2
Requires-Dist: pydantic >=2.0.2
